esig/backends.py
esig/libiomp5md.dll
esig/recombine.dll
esig/recombine.lib
esig/tosig.py
esig/VERSION
esig/_tosig.cp37-win_amd64.pyd
esig/__init__.py
esig-0.9.8.3.data/data/CHANGELOG
esig-0.9.8.3.data/data/CMakeLists.txt
esig-0.9.8.3.data/data/libalgebra/CMakeLists.txt
esig-0.9.8.3.data/data/libalgebra/LibalgebraConfig.cmake.in
esig-0.9.8.3.data/data/libalgebra/README.md
esig-0.9.8.3.data/data/libalgebra/addons/clone_unordered_map.h
esig-0.9.8.3.data/data/libalgebra/addons/gmpwrapper.h
esig-0.9.8.3.data/data/libalgebra/addons/sized_unordered_map.h
esig-0.9.8.3.data/data/libalgebra/cmake/Modules/FindBignum.cmake
esig-0.9.8.3.data/data/libalgebra/libalgebra/algebra.h
esig-0.9.8.3.data/data/libalgebra/libalgebra/alg_types.h
esig-0.9.8.3.data/data/libalgebra/libalgebra/basis_traits.h
esig-0.9.8.3.data/data/libalgebra/libalgebra/constlog2.h
esig-0.9.8.3.data/data/libalgebra/libalgebra/constpower.h
esig-0.9.8.3.data/data/libalgebra/libalgebra/hall_set.h
esig-0.9.8.3.data/data/libalgebra/libalgebra/implementation_types.h
esig-0.9.8.3.data/data/libalgebra/libalgebra/libalgebra.h
esig-0.9.8.3.data/data/libalgebra/libalgebra/lie.h
esig-0.9.8.3.data/data/libalgebra/libalgebra/lie_basis.h
esig-0.9.8.3.data/data/libalgebra/libalgebra/monomial_basis.h
esig-0.9.8.3.data/data/libalgebra/libalgebra/multiplication_helpers.h
esig-0.9.8.3.data/data/libalgebra/libalgebra/multi_polynomial.h
esig-0.9.8.3.data/data/libalgebra/libalgebra/polynomials.h
esig-0.9.8.3.data/data/libalgebra/libalgebra/poly_basis.h
esig-0.9.8.3.data/data/libalgebra/libalgebra/poly_lie.h
esig-0.9.8.3.data/data/libalgebra/libalgebra/poly_lie_basis.h
esig-0.9.8.3.data/data/libalgebra/libalgebra/tensor.h
esig-0.9.8.3.data/data/libalgebra/libalgebra/tensor_basis.h
esig-0.9.8.3.data/data/libalgebra/libalgebra/utils.h
esig-0.9.8.3.data/data/libalgebra/libalgebra/_tensor_basis.h
esig-0.9.8.3.data/data/libalgebra/libalgebra/basis/basis.h
esig-0.9.8.3.dist-info/AUTHORS
esig-0.9.8.3.dist-info/DELVEWHEEL
esig-0.9.8.3.dist-info/LICENSE
esig-0.9.8.3.dist-info/METADATA
esig-0.9.8.3.dist-info/RECORD
esig-0.9.8.3.dist-info/top_level.txt
esig-0.9.8.3.dist-info/WHEEL
