Metadata-Version: 2.1
Name: esig
Version: 0.9.8.3
Summary: This package provides "rough path" tools for analysing vector time series.
Home-page: http://esig.readthedocs.io/en/latest/
Author: Terry Lyons
Author-email: software@lyonstech.net
License: GPLv3
Keywords: data streams rough paths signatures
Classifier: Development Status :: 4 - Beta
Classifier: Intended Audience :: Developers
Classifier: Programming Language :: Python :: 3
Classifier: Programming Language :: Python :: 3.5
Classifier: Programming Language :: Python :: 3.6
Classifier: Programming Language :: Python :: 3.7
Classifier: Programming Language :: Python :: 3.8
Classifier: Programming Language :: Python :: 3.9
Classifier: Topic :: Scientific/Engineering :: Mathematics
Provides-Extra: iisignature
License-File: LICENSE
License-File: AUTHORS
